torch_simple_timing/__init__.py
torch_simple_timing/clock.py
torch_simple_timing/timer.py
torch_simple_timing/utils.py
torch_simple_timing-0.1.5.dist-info/LICENSE
torch_simple_timing-0.1.5.dist-info/WHEEL
torch_simple_timing-0.1.5.dist-info/METADATA
torch_simple_timing-0.1.5.dist-info/RECORD
