Metadata-Version: 2.1
Name: torch-simple-timing
Version: 0.1.5
Summary: A simple package to time CPU/GPU/Multi-GPU ops
License: MIT
Author: vict0rsch
Author-email: vsch@pm.me
Requires-Python: >=3.8.1,<4.0.0
Classifier: License :: OSI Approved :: MIT License
Classifier: Programming Language :: Python :: 3
Classifier: Programming Language :: Python :: 3.9
Classifier: Programming Language :: Python :: 3.10
Classifier: Programming Language :: Python :: 3.11
Requires-Dist: torch (>=1.11)
